<annotation>
  <folder />
  <filename>06_29_14_45_20_0011_5_2-PX.jpg</filename>
  <path />
  <source>
      <database>Unknown</database>
  </source>
  <size>
      <width>850</width>
      <height>350</height>
      <depth>3</depth>
  </size>
  <segmented>0</segmented>
  <object>
      <name>DL</name>
      <pose>Unspecified</pose>
      <truncated>0</truncated>
      <difficult>0</difficult>
      <bndbox>
          <xmin>664</xmin>
          <ymin>122</ymin>
          <xmax>850</xmax>
          <ymax>186</ymax>
      </bndbox>
  </object>
  <object>
      <name>CL</name>
      <pose>Unspecified</pose>
      <truncated>0</truncated>
      <difficult>0</difficult>
      <bndbox>
          <xmin>792</xmin>
          <ymin>19</ymin>
          <xmax>849</xmax>
          <ymax>82</ymax>
      </bndbox>
  </object>
  <object>
      <name>TS</name>
      <pose>Unspecified</pose>
      <truncated>0</truncated>
      <difficult>0</difficult>
      <bndbox>
          <xmin>440</xmin>
          <ymin>134</ymin>
          <xmax>655</xmax>
          <ymax>236</ymax>
      </bndbox>
  </object>
</annotation>