<annotation>
  <folder />
  <filename>06_28_14_24_20_0008_1_2-PX.jpg</filename>
  <path />
  <source>
      <database>Unknown</database>
  </source>
  <size>
      <width>850</width>
      <height>350</height>
      <depth>3</depth>
  </size>
  <segmented>0</segmented>
  <object>
      <name>CL</name>
      <pose>Unspecified</pose>
      <truncated>0</truncated>
      <difficult>0</difficult>
      <bndbox>
          <xmin>765</xmin>
          <ymin>77</ymin>
          <xmax>848</xmax>
          <ymax>148</ymax>
      </bndbox>
  </object>
  <object>
      <name>TS</name>
      <pose>Unspecified</pose>
      <truncated>0</truncated>
      <difficult>0</difficult>
      <bndbox>
          <xmin>547</xmin>
          <ymin>132</ymin>
          <xmax>779</xmax>
          <ymax>240</ymax>
      </bndbox>
  </object>
</annotation>