<annotation>
  <folder />
  <filename>06_27_08_13_49_0585_4_3-XH_flip.jpg</filename>
  <path />
  <source>
      <database>Unknown</database>
  </source>
  <size>
      <width>850</width>
      <height>350</height>
      <depth>3</depth>
  </size>
  <segmented>0</segmented>
  <object>
      <name>DL</name>
      <pose>Unspecified</pose>
      <truncated>0</truncated>
      <difficult>0</difficult>
      <bndbox>
          <xmin>479</xmin>
          <ymin>124</ymin>
          <xmax>597</xmax>
          <ymax>180</ymax>
      </bndbox>
  </object>
  <object>
      <name>CL</name>
      <pose>Unspecified</pose>
      <truncated>0</truncated>
      <difficult>0</difficult>
      <bndbox>
          <xmin>540</xmin>
          <ymin>57</ymin>
          <xmax>632</xmax>
          <ymax>118</ymax>
      </bndbox>
  </object>
  <object>
      <name>TE</name>
      <pose>Unspecified</pose>
      <truncated>0</truncated>
      <difficult>0</difficult>
      <bndbox>
          <xmin>171</xmin>
          <ymin>103</ymin>
          <xmax>277</xmax>
          <ymax>222</ymax>
      </bndbox>
  </object>
</annotation>