<annotation>
  <folder />
  <filename>07_04_17_04_45_0668_1_2-PX_flip.jpg</filename>
  <path />
  <source>
      <database>Unknown</database>
  </source>
  <size>
      <width>850</width>
      <height>350</height>
      <depth>3</depth>
  </size>
  <segmented>0</segmented>
  <object>
      <name>DL</name>
      <pose>Unspecified</pose>
      <truncated>0</truncated>
      <difficult>0</difficult>
      <bndbox>
          <xmin>694</xmin>
          <ymin>111</ymin>
          <xmax>849</xmax>
          <ymax>168</ymax>
      </bndbox>
  </object>
  <object>
      <name>CL</name>
      <pose>Unspecified</pose>
      <truncated>0</truncated>
      <difficult>0</difficult>
      <bndbox>
          <xmin>802</xmin>
          <ymin>13</ymin>
          <xmax>850</xmax>
          <ymax>74</ymax>
      </bndbox>
  </object>
  <object>
      <name>TS</name>
      <pose>Unspecified</pose>
      <truncated>0</truncated>
      <difficult>0</difficult>
      <bndbox>
          <xmin>523</xmin>
          <ymin>105</ymin>
          <xmax>712</xmax>
          <ymax>195</ymax>
      </bndbox>
  </object>
</annotation>