<annotation>
  <folder />
  <filename>07_04_17_04_45_0394_1_1-TX.jpg</filename>
  <path />
  <source>
      <database>Unknown</database>
  </source>
  <size>
      <width>850</width>
      <height>350</height>
      <depth>3</depth>
  </size>
  <segmented>0</segmented>
  <object>
      <name>CL</name>
      <pose>Unspecified</pose>
      <truncated>0</truncated>
      <difficult>0</difficult>
      <bndbox>
          <xmin>716</xmin>
          <ymin>10</ymin>
          <xmax>810</xmax>
          <ymax>74</ymax>
      </bndbox>
  </object>
  <object>
      <name>TS</name>
      <pose>Unspecified</pose>
      <truncated>0</truncated>
      <difficult>0</difficult>
      <bndbox>
          <xmin>366</xmin>
          <ymin>151</ymin>
          <xmax>492</xmax>
          <ymax>205</ymax>
      </bndbox>
  </object>
</annotation>