<annotation>
  <folder />
  <filename>07_04_17_04_45_0056_1_1-TX.jpg</filename>
  <path />
  <source>
      <database>Unknown</database>
  </source>
  <size>
      <width>850</width>
      <height>350</height>
      <depth>3</depth>
  </size>
  <segmented>0</segmented>
  <object>
      <name>CL</name>
      <pose>Unspecified</pose>
      <truncated>0</truncated>
      <difficult>0</difficult>
      <bndbox>
          <xmin>584</xmin>
          <ymin>49</ymin>
          <xmax>682</xmax>
          <ymax>116</ymax>
      </bndbox>
  </object>
  <object>
      <name>TTCW</name>
      <pose>Unspecified</pose>
      <truncated>0</truncated>
      <difficult>0</difficult>
      <bndbox>
          <xmin>388</xmin>
          <ymin>136</ymin>
          <xmax>547</xmax>
          <ymax>219</ymax>
      </bndbox>
  </object>
  <object>
      <name>TS</name>
      <pose>Unspecified</pose>
      <truncated>0</truncated>
      <difficult>0</difficult>
      <bndbox>
          <xmin>384</xmin>
          <ymin>163</ymin>
          <xmax>494</xmax>
          <ymax>217</ymax>
      </bndbox>
  </object>
</annotation>