<annotation>
  <folder />
  <filename>07_15_11_16_36_0013_6_2-PX_flip.jpg</filename>
  <path />
  <source>
      <database>Unknown</database>
  </source>
  <size>
      <width>850</width>
      <height>350</height>
      <depth>3</depth>
  </size>
  <segmented>0</segmented>
  <object>
      <name>CL</name>
      <pose>Unspecified</pose>
      <truncated>0</truncated>
      <difficult>0</difficult>
      <bndbox>
          <xmin>800</xmin>
          <ymin>35</ymin>
          <xmax>849</xmax>
          <ymax>114</ymax>
      </bndbox>
  </object>
  <object>
      <name>TS</name>
      <pose>Unspecified</pose>
      <truncated>0</truncated>
      <difficult>0</difficult>
      <bndbox>
          <xmin>487</xmin>
          <ymin>166</ymin>
          <xmax>658</xmax>
          <ymax>234</ymax>
      </bndbox>
  </object>
</annotation>