<annotation>
  <folder />
  <filename>07_15_14_20_56_0055_6_0-GD_flip.jpg</filename>
  <path />
  <source>
      <database>Unknown</database>
  </source>
  <size>
      <width>850</width>
      <height>350</height>
      <depth>3</depth>
  </size>
  <segmented>0</segmented>
  <object>
      <name>DL</name>
      <pose>Unspecified</pose>
      <truncated>0</truncated>
      <difficult>0</difficult>
      <bndbox>
          <xmin>576</xmin>
          <ymin>85</ymin>
          <xmax>711</xmax>
          <ymax>139</ymax>
      </bndbox>
  </object>
  <object>
      <name>CL</name>
      <pose>Unspecified</pose>
      <truncated>0</truncated>
      <difficult>0</difficult>
      <bndbox>
          <xmin>809</xmin>
          <ymin>36</ymin>
          <xmax>850</xmax>
          <ymax>116</ymax>
      </bndbox>
  </object>
</annotation>