<annotation>
  <folder />
  <filename>07_15_11_09_42_0041_2_0-GD_flip.jpg</filename>
  <path />
  <source>
      <database>Unknown</database>
  </source>
  <size>
      <width>850</width>
      <height>350</height>
      <depth>3</depth>
  </size>
  <segmented>0</segmented>
  <object>
      <name>DL</name>
      <pose>Unspecified</pose>
      <truncated>0</truncated>
      <difficult>0</difficult>
      <bndbox>
          <xmin>599</xmin>
          <ymin>118</ymin>
          <xmax>726</xmax>
          <ymax>170</ymax>
      </bndbox>
  </object>
  <object>
      <name>CL</name>
      <pose>Unspecified</pose>
      <truncated>0</truncated>
      <difficult>0</difficult>
      <bndbox>
          <xmin>778</xmin>
          <ymin>18</ymin>
          <xmax>850</xmax>
          <ymax>80</ymax>
      </bndbox>
  </object>
</annotation>